vofs/CacheMetaData.py
vofs/CadcCache.py
vofs/SharedLock.py
vofs/__init__.py
vofs/mountvofs.py
vofs/utils.py
vofs/version.py
vofs/vofs.py
vofs/tests/__init__.py
vofs/tests/test_cache_metadata.py
vofs/tests/test_cadc_cache.py
vofs/tests/test_vofs.py
vofs-3.1.dist-info/METADATA
vofs-3.1.dist-info/WHEEL
vofs-3.1.dist-info/entry_points.txt
vofs-3.1.dist-info/top_level.txt
vofs-3.1.dist-info/RECORD
