Metadata-Version: 2.1
Name: vofs
Version: 3.1
Summary: Class Libraries for VOSpace file system
Home-page: https://www.canfar.net/en/docs/storage
Author: JJ Kavelaars, Canadian Astronomy Data Centre
Author-email: cadc@nrc-cnrc.gc.ca
License: AGPLv3
Project-URL: Source, https://github.com/opencadc/vostools
Project-URL: Travis CI, https://travis-ci.org/opencadc/vostools
Project-URL: Issues, https://github.com/opencadc/vostools/issues
Project-URL: VOSpace Standard, http://www.ivoa.net/documents/VOSpace/
Platform: UNKNOWN
Classifier: Natural Language :: English
Classifier: License :: OSI Approved :: GNU Affero General Public License v3
Classifier: Programming Language :: Python
Classifier: Programming Language :: Python :: 3
Requires-Python: !=3.0.*, !=3.1.*, !=3.2.*, !=3.4, <4
Requires-Dist: vos (>=3.3.7)
Requires-Dist: BitVector (<4.0,>=3.4.4)
Requires-Dist: fusepy (>=2.0.4)
Provides-Extra: test
Requires-Dist: pytest (>=4.6) ; extra == 'test'
Requires-Dist: pytest-cov (>=2.5.1) ; extra == 'test'
Requires-Dist: flake8 (>=3.4.1) ; extra == 'test'
Requires-Dist: future (>=0.16.0) ; extra == 'test'
Requires-Dist: mock (>=2.0.0) ; extra == 'test'
